{
  "output_id": "osmo_usd",
  "templates": [
    {
      "template_id": "response_handler",
      "adapters": [
        {
          "adapter": "unresponsive_handler",
          "config": {
            "strategy": "use_last",
            "grace_duration": "120"
          }
        },
        {
          "adapter": "unchanged_handler",
          "config": {
            "strategy": "nullify",
            "threshold_duration": "900"
          }
        }
      ]
    }
  ],
  "jobs": [
    {
      "output_id": "pyth_osmo_usd_8",
      "adapters": [
        {
          "adapter": "fetcher_multiple",
          "config": {
            "custom_node_url_key": "pyth_osmo_usd",
            "default_node_host": "https://hermes.pyth.network",
            "default_node_path": "/api/latest_price_feeds?ids[]=0x5867f5683c757393a0670ef0f701490950fe93fdb006d181c8265a831ac0c5c6",
            "paths": "[\"0.price.price\"]",
            "timeout": "10"
          }
        },
        {
          "template": "response_handler"
        }
      ]
    },
    {
      "output_id": "pyth_osmo_usd",
      "input_id": "pyth_osmo_usd_8",
      "adapter": "decimal_handler",
      "config": {
        "operation": "decrease",
        "exponent": "8"
      }
    },
    {
      "output_id": "coinbase_osmo_usd",
      "adapters": [
        {
          "adapter": "fetcher_multiple",
          "config": {
            "custom_node_url_key": "coinbase_osmo_usd",
            "default_node_host": "https://api.exchange.coinbase.com",
            "default_node_path": "/products/OSMO-USD/ticker",
            "paths": "[\"price\"]",
            "timeout": "10"
          }
        },
        {
          "template": "response_handler"
        }
      ]
    },
    {
      "output_id": "binance_osmo_usdt",
      "adapters": [
        {
          "adapter": "fetcher_multiple",
          "config": {
            "custom_node_url_key": "binance_osmo_usdt",
            "default_node_host": "https://api-binance-proxy.carbon.network",
            "default_node_path": "/api/v3/ticker/price?symbol=OSMOUSDT",
            "paths": "[\"price\"]",
            "timeout": "10"
          }
        },
        {
          "template": "response_handler"
        }
      ]
    },
    {
      "output_id": "usdt_usd",
      "adapters": [
        {
          "adapter": "oracle_result_fetcher",
          "config": {
            "oracle_id": ".CUSDT",
            "stale_allowance": "900"
          }
        }
      ]
    },
    {
      "output_id": "binance_osmo_usd",
      "adapter": "math_filter",
      "config": {
        "operation": "multiply",
        "input_ids": "[\"binance_osmo_usdt\",\"usdt_usd\"]"
      }
    },
    {
      "input_id": "pyth_osmo_usd",
      "output_id": "pyth_osmo_usd",
      "adapter": "median_filter",
      "config": {
        "strategy": "nullify",
        "value_ids": "[\"pyth_osmo_usd\", \"coinbase_osmo_usd\", \"binance_osmo_usd\"]",
        "tolerance_percentage": "3"
      }
    },
    {
      "input_id": "coinbase_osmo_usd",
      "output_id": "coinbase_osmo_usd",
      "adapter": "median_filter",
      "config": {
        "strategy": "nullify",
        "value_ids": "[\"pyth_osmo_usd\", \"coinbase_osmo_usd\", \"binance_osmo_usd\"]",
        "tolerance_percentage": "3"
      }
    },
    {
      "input_id": "binance_osmo_usd",
      "output_id": "binance_osmo_usd",
      "adapter": "median_filter",
      "config": {
        "strategy": "nullify",
        "value_ids": "[\"pyth_osmo_usd\", \"coinbase_osmo_usd\", \"binance_osmo_usd\"]",
        "tolerance_percentage": "3"
      }
    },
    {
      "output_id": "osmo_usd",
      "adapter": "weighted_average",
      "config": {
        "value_ids": "[\"pyth_osmo_usd\", \"coinbase_osmo_usd\", \"binance_osmo_usd\"]",
        "weights": "[0.3, 0.3, 0.4]"
      }
    },
    {
      "output_id": "osmo_usd",
      "input_id": "osmo_usd",
      "adapter": "float_handler",
      "config": {
        "operation": "round",
        "precision": "6"
      }
    }
  ]
}